{
  "_note1": "KEEP THIS FILE! Check it into a version control system (VCS) like git.",
  "_note2": "ObjectBox manages crucial IDs for your object model. See docs for details.",
  "_note3": "If you have VCS merge conflicts, you must resolve them according to ObjectBox docs.",
  "entities": [
    {
      "id": "1:7803930932746315919",
      "lastPropertyId": "4:1924336567525146288",
      "name": "Note",
      "properties": [
        {
          "id": "1:8593323585746626424",
          "name": "id"
        },
        {
          "id": "2:623966032411846350",
          "name": "text"
        },
        {
          "id": "3:8812576090470392497",
          "name": "comment"
        },
        {
          "id": "4:1924336567525146288",
          "name": "date"
        }
      ]
    }
  ],
  "lastEntityId": "1:7803930932746315919",
  "lastIndexId": "0:0",
  "lastSequenceId": "0:0",
  "modelVersion": 2,
  "retiredEntityUids": [],
  "retiredIndexUids": [],
  "retiredPropertyUids": [],
  "version": 1
}